hdpws/__init__.py
hdpws/__main__.py
hdpws/dateinterval.py
hdpws/hdpws.py
hdpws/resourcetype.py
hdpws/spase.py
hdpws/spasehtmlparser.py
hdpws-0.6.26.dist-info/licenses/LICENSE
hdpws-0.6.26.dist-info/METADATA
hdpws-0.6.26.dist-info/WHEEL
hdpws-0.6.26.dist-info/top_level.txt
hdpws-0.6.26.dist-info/RECORD
