Metadata-Version: 2.4
Name: hdpws
Version: 0.6.26
Summary: NASA's Heliophysics Data Portal Web Service Client Library
Home-page: https://heliophysicsdata.gsfc.nasa.gov/WebServices
Author: Bernie Harris
Author-email: NASA-SPDF-Support@nasa.onmicrosoft.com
License: NOSA
Keywords: heliophysics,spase,space physics,spdf,hdp
Classifier: Development Status :: 3 - Alpha
Classifier: Environment :: Console
Classifier: Environment :: Web Environment
Classifier: Intended Audience :: End Users/Desktop
Classifier: Intended Audience :: Developers
Classifier: Intended Audience :: System Administrators
Classifier: Operating System :: MacOS :: MacOS X
Classifier: Operating System :: Microsoft :: Windows
Classifier: Operating System :: POSIX
Classifier: Programming Language :: Python
Classifier: Topic :: Scientific/Engineering :: Physics
Classifier: Topic :: Software Development :: Libraries :: Python Modules
License-File: LICENSE
Requires-Dist: python-dateutil>=2.8.0
Requires-Dist: requests>=2.20
Requires-Dist: urllib3>=1.26.14
Dynamic: author
Dynamic: author-email
Dynamic: classifier
Dynamic: description
Dynamic: description-content-type
Dynamic: home-page
Dynamic: keywords
Dynamic: license
Dynamic: license-file
Dynamic: requires-dist
Dynamic: summary
